codestare/proto/__init__.py
codestare/proto/compile.py
codestare_proto_plus-0.0.5.dist-info/LICENSE.rst
codestare_proto_plus-0.0.5.dist-info/METADATA
codestare_proto_plus-0.0.5.dist-info/WHEEL
codestare_proto_plus-0.0.5.dist-info/entry_points.txt
codestare_proto_plus-0.0.5.dist-info/top_level.txt
codestare_proto_plus-0.0.5.dist-info/RECORD
