Metadata-Version: 2.1
Name: codestare-proto-plus
Version: 0.0.5
Summary: "Protoc plugin to compile proto plus python classes"
Home-page: https://github.com/saggitar/proto-plus-plugin.git
Author: Maximilian Schmidt
Author-email: ga97lul@mytum.de
Keywords: protobuf,proto-plus
Classifier: Programming Language :: Python :: 3
Requires-Python: >=3.7
License-File: LICENSE.rst
Requires-Dist: proto-plus
Requires-Dist: importlib-metadata ; python_version <= "3.7"
